Metadata-Version: 2.4
Name: twidgets
Version: 2.0.0
Summary: A tool to design and run dynamic, customizable dashboards directly inside your terminal.
Author-email: IceWizard7 <mrrioes.dc@gmail.com>
License-Expression: Apache-2.0
Project-URL: Homepage, https://github.com/IceWizard7/terminal-widgets
Project-URL: Documentation, https://github.com/IceWizard7/terminal-widgets/blob/main/docs/index.md
Project-URL: Source, https://github.com/IceWizard7/terminal-widgets
Project-URL: Issues, https://github.com/IceWizard7/terminal-widgets/issues
Classifier: Programming Language :: Python :: 3
Classifier: Programming Language :: Python :: 3.10
Classifier: Programming Language :: Python :: 3.11
Classifier: Programming Language :: Python :: 3.12
Classifier: Programming Language :: Python :: 3.13
Classifier: Programming Language :: Python :: 3.14
Classifier: Environment :: Console
Classifier: Environment :: Console :: Curses
Classifier: Operating System :: POSIX
Classifier: Operating System :: MacOS
Classifier: Operating System :: Unix
Classifier: Topic :: Terminals
Classifier: Topic :: System :: Monitoring
Classifier: Topic :: Utilities
Requires-Python: >=3.10
License-File: LICENSE
Requires-Dist: psutil~=7.2.1
Requires-Dist: requests~=2.32.5
Requires-Dist: feedparser~=6.0.12
Requires-Dist: PyYAML~=6.0.3
Requires-Dist: python-dotenv~=1.2.1
Dynamic: license-file
